faaspectre/__init__.py
faaspectre/application/__init__.py
faaspectre/application/config.py
faaspectre/application/logger.py
faaspectre/application/ports/__init__.py
faaspectre/application/ports/instrumentation.py
faaspectre/application/ports/metric_storage.py
faaspectre/application/ports/serializer.py
faaspectre/application/use_case/__init__.py
faaspectre/application/use_case/job_execution_reporter.py
faaspectre/domain/__init__.py
faaspectre/domain/exceptions.py
faaspectre/domain/models.py
faaspectre/domain/status.py
faaspectre/domain/validators.py
faaspectre/infrastructure/__init__.py
faaspectre/infrastructure/adapters/__init__.py
faaspectre/infrastructure/adapters/instrumentation/__init__.py
faaspectre/infrastructure/adapters/instrumentation/psutil_instrumentation.py
faaspectre/infrastructure/adapters/serializer/__init__.py
faaspectre/infrastructure/adapters/serializer/firestore_serializer.py
faaspectre/infrastructure/adapters/storage/__init__.py
faaspectre/infrastructure/adapters/storage/firestore_metric_storage.py
faaspectre/infrastructure/utils/__init__.py
faaspectre/infrastructure/utils/firestore_client.py
faaspectre/utils/__init__.py
faaspectre/utils/datetime_utils.py
faaspectre/utils/error_formatter.py
faaspectre/utils/logger.py
faaspectre/utils/memory_tracker.py
faaspectre/utils/singleton.py
faaspectre-0.0.1.dist-info/METADATA
faaspectre-0.0.1.dist-info/WHEEL
faaspectre-0.0.1.dist-info/top_level.txt
faaspectre-0.0.1.dist-info/RECORD
