Metadata-Version: 2.4
Name: faaspectre
Version: 0.0.1
Summary: FaaS Telemetric Reporter - Job Execution Metrics Library
Home-page: https://github.com/yourusername/faaspectre
Author: Iván Huerta
Author-email: ivan.huerta.h@gmail.com
License: Unlicense
Keywords: faas serverless metrics telemetry firestore google-cloud monitoring
Classifier: Development Status :: 3 - Alpha
Classifier: Intended Audience :: Developers
Classifier: License :: Public Domain
Classifier: Operating System :: OS Independent
Classifier: Programming Language :: Python :: 3
Classifier: Programming Language :: Python :: 3.8
Classifier: Programming Language :: Python :: 3.9
Classifier: Programming Language :: Python :: 3.10
Classifier: Programming Language :: Python :: 3.11
Classifier: Programming Language :: Python :: 3.12
Classifier: Topic :: Software Development :: Libraries :: Python Modules
Classifier: Topic :: System :: Monitoring
Requires-Python: >=3.8
Provides-Extra: all
Requires-Dist: marshmallow_dataclass==8.3.2; extra == "all"
Requires-Dist: marshmallow-enum==1.5.1; extra == "all"
Requires-Dist: google-cloud-firestore==2.4.0; extra == "all"
Requires-Dist: psutil>=5.8.0; extra == "all"
Provides-Extra: faasjob
Requires-Dist: marshmallow_dataclass==8.3.2; extra == "faasjob"
Requires-Dist: marshmallow-enum==1.5.1; extra == "faasjob"
Requires-Dist: google-cloud-firestore==2.4.0; extra == "faasjob"
Requires-Dist: psutil>=5.8.0; extra == "faasjob"
Provides-Extra: datastore
Requires-Dist: marshmallow_dataclass==8.3.2; extra == "datastore"
Requires-Dist: marshmallow-enum==1.5.1; extra == "datastore"
Requires-Dist: google-cloud-firestore==2.4.0; extra == "datastore"
Dynamic: author
Dynamic: author-email
Dynamic: classifier
Dynamic: description
Dynamic: description-content-type
Dynamic: home-page
Dynamic: keywords
Dynamic: license
Dynamic: provides-extra
Dynamic: requires-python
Dynamic: summary
